gnordvpn_sprokkel78/CHANGELOG.txt
gnordvpn_sprokkel78/LICENSE
gnordvpn_sprokkel78/README.md
gnordvpn_sprokkel78/__init__.py
gnordvpn_sprokkel78/gnordvpn.css
gnordvpn_sprokkel78/gnordvpn.desktop
gnordvpn_sprokkel78/gnordvpn.png
gnordvpn_sprokkel78/gnordvpn.py
gnordvpn_sprokkel78/gnordvpn.svg
gnordvpn_sprokkel78/install.sh
gnordvpn_sprokkel78/uninstall.sh
gnordvpn_sprokkel78/images/b_allowlist.png
gnordvpn_sprokkel78/images/b_help.png
gnordvpn_sprokkel78/images/b_menu.png
gnordvpn_sprokkel78/images/b_meshnet.png
gnordvpn_sprokkel78/images/b_pause.png
gnordvpn_sprokkel78/images/b_peers.png
gnordvpn_sprokkel78/images/b_play.png
gnordvpn_sprokkel78/images/b_settings.png
gnordvpn_sprokkel78/screenshots/gnordvpn-1.png
gnordvpn_sprokkel78/screenshots/gnordvpn-2.png
gnordvpn_sprokkel78/screenshots/gnordvpn-3.png
gnordvpn_sprokkel78/screenshots/gnordvpn-4.png
gnordvpn_sprokkel78-1.3.3.dist-info/METADATA
gnordvpn_sprokkel78-1.3.3.dist-info/WHEEL
gnordvpn_sprokkel78-1.3.3.dist-info/licenses/LICENSE
gnordvpn_sprokkel78-1.3.3.dist-info/RECORD
